<?xml version="1.0"?>
<trafficlist>
<!-- Eagle-EGLL-EGHQ-EGPF -->
    <aircraft>
        <model>Aircraft/Britannia/brit-G-ARKA.xml</model>
        <livery>EG</livery>
        <airline>EG</airline>
        <home-port>EGLL</home-port>
        <required-aircraft>brit-G-ARKA04</required-aircraft>
        <actype>Britannia</actype>
        <offset>0</offset>
        <radius>18</radius>
        <flighttype>gate</flighttype>
        <performance-class>turboprop_transport</performance-class>
        <registration>G-ARKA04</registration>
        <heavy>false</heavy>
    </aircraft>
    <flight>
        <callsign>EAGLE-781</callsign>
        <required-aircraft>brit-G-ARKA04</required-aircraft>
        <fltrules>IFR</fltrules>
        <departure>
            <port>EGLL</port>
            <time>11:10:00</time>
        </departure>
        <cruise-alt>190</cruise-alt>
        <arrival>
            <port>EGHQ</port>
            <time>12:10:00</time>
        </arrival>
        <repeat>24Hr</repeat>
    </flight>
    <flight>
        <callsign>EAGLE-792</callsign>
        <required-aircraft>brit-G-ARKA04</required-aircraft>
        <fltrules>IFR</fltrules>
        <departure>
            <port>EGHQ</port>
            <time>12:55:00</time>
        </departure>
        <cruise-alt>180</cruise-alt>
        <arrival>
            <port>EGPF</port>
            <time>14:35:00</time>
        </arrival>
        <repeat>24Hr</repeat>
    </flight>
    <flight>
        <callsign>EAGLE-791</callsign>
        <required-aircraft>brit-G-ARKA04</required-aircraft>
        <fltrules>IFR</fltrules>
        <departure>
            <port>EGPF</port>
            <time>15:55:00</time>
        </departure>
        <cruise-alt>190</cruise-alt>
        <arrival>
            <port>EGHQ</port>
            <time>17:35:00</time>
        </arrival>
        <repeat>24Hr</repeat>
    </flight>
    <flight>
        <callsign>EAGLE-782</callsign>
        <required-aircraft>brit-G-ARKA04</required-aircraft>
        <fltrules>IFR</fltrules>
        <departure>
            <port>EGHQ</port>
            <time>18:20:00</time>
        </departure>
        <cruise-alt>180</cruise-alt>
        <arrival>
            <port>EGLL</port>
            <time>19:20:00</time>
        </arrival>
        <repeat>24Hr</repeat>
    </flight>
</trafficlist>